<?xml version="1.0" encoding="utf-8"?>
<LanguageData>

  <Gastronomy_Serviced.stages.0.label>awful service</Gastronomy_Serviced.stages.0.label>
  <Gastronomy_Serviced.stages.1.label>bad service</Gastronomy_Serviced.stages.1.label>
  <Gastronomy_Serviced.stages.2.label>decent service</Gastronomy_Serviced.stages.2.label>
  <Gastronomy_Serviced.stages.3.label>good service</Gastronomy_Serviced.stages.3.label>
  <Gastronomy_Serviced.stages.4.label>excellent service</Gastronomy_Serviced.stages.4.label>

  <Gastronomy_ServicedMood.stages.0.label>had awful service</Gastronomy_ServicedMood.stages.0.label>
  <Gastronomy_ServicedMood.stages.0.description>I've been treated awfully.</Gastronomy_ServicedMood.stages.0.description>
  <Gastronomy_ServicedMood.stages.1.label>had bad service</Gastronomy_ServicedMood.stages.1.label>
  <Gastronomy_ServicedMood.stages.1.description>I've been treated poorly.</Gastronomy_ServicedMood.stages.1.description>
  <Gastronomy_ServicedMood.stages.2.label>had decent service</Gastronomy_ServicedMood.stages.2.label>
  <Gastronomy_ServicedMood.stages.2.description>I've been treated decently.</Gastronomy_ServicedMood.stages.2.description>
  <Gastronomy_ServicedMood.stages.3.label>had good service</Gastronomy_ServicedMood.stages.3.label>
  <Gastronomy_ServicedMood.stages.3.description>I've been treated well.</Gastronomy_ServicedMood.stages.3.description>
  <Gastronomy_ServicedMood.stages.4.label>had excellent service</Gastronomy_ServicedMood.stages.4.label>
  <Gastronomy_ServicedMood.stages.4.description>I've been treated exceptionally well.</Gastronomy_ServicedMood.stages.4.description>
  
  <Gastronomy_BoughtFood.stages.0.label>received free food</Gastronomy_BoughtFood.stages.0.label>
  <Gastronomy_BoughtFood.stages.0.description>The food is free!</Gastronomy_BoughtFood.stages.0.description>
  <Gastronomy_BoughtFood.stages.1.label>received very cheap food</Gastronomy_BoughtFood.stages.1.label>
  <Gastronomy_BoughtFood.stages.1.description>The food is very cheap.</Gastronomy_BoughtFood.stages.1.description>
  <Gastronomy_BoughtFood.stages.2.label>received cheap food</Gastronomy_BoughtFood.stages.2.label>
  <Gastronomy_BoughtFood.stages.2.description>The food is cheap.</Gastronomy_BoughtFood.stages.2.description>
  <Gastronomy_BoughtFood.stages.3.label>received food</Gastronomy_BoughtFood.stages.3.label>
  <Gastronomy_BoughtFood.stages.3.description>The food is affordable.</Gastronomy_BoughtFood.stages.3.description>
  <Gastronomy_BoughtFood.stages.4.label>received expensive food</Gastronomy_BoughtFood.stages.4.label>
  <Gastronomy_BoughtFood.stages.4.description>The food is expensive.</Gastronomy_BoughtFood.stages.4.description>
  <Gastronomy_BoughtFood.stages.5.label>received very expensive food</Gastronomy_BoughtFood.stages.5.label>
  <Gastronomy_BoughtFood.stages.5.description>The food is very expensive.</Gastronomy_BoughtFood.stages.5.description>

</LanguageData>
